[
  {
    "text": "해",
    "hanja": [
      {
        "text": "㰩",
        "meaning": "해",
        "strokeCount": "10"
      },
      {
        "text": "䀭",
        "meaning": "해",
        "strokeCount": "11"
      },
      {
        "text": "亥",
        "meaning": "열두째지지",
        "strokeCount": "6"
      },
      {
        "text": "侅",
        "meaning": "이상할",
        "strokeCount": "8"
      },
      {
        "text": "偕",
        "meaning": "함께",
        "strokeCount": "11"
      },
      {
        "text": "咍",
        "meaning": "비웃을",
        "strokeCount": "8"
      },
      {
        "text": "咳",
        "meaning": "기침",
        "strokeCount": "9"
      },
      {
        "text": "垓",
        "meaning": "땅가장자",
        "strokeCount": "9"
      },
      {
        "text": "奚",
        "meaning": "어찌,어느곳",
        "strokeCount": "10"
      },
      {
        "text": "姟",
        "meaning": "해",
        "strokeCount": "9"
      },
      {
        "text": "孩",
        "meaning": "어린아이",
        "strokeCount": "9"
      },
      {
        "text": "害",
        "meaning": "해할,시기할",
        "strokeCount": "10"
      },
      {
        "text": "嶰",
        "meaning": "골짜기이름",
        "strokeCount": "16"
      },
      {
        "text": "廨",
        "meaning": "공해",
        "strokeCount": "16"
      },
      {
        "text": "懈",
        "meaning": "게으를",
        "strokeCount": "16"
      },
      {
        "text": "晐",
        "meaning": "갖출",
        "strokeCount": "10"
      },
      {
        "text": "楷",
        "meaning": "본,해서",
        "strokeCount": "13"
      },
      {
        "text": "欬",
        "meaning": "기침",
        "strokeCount": "10"
      },
      {
        "text": "海",
        "meaning": "바다",
        "strokeCount": "10"
      },
      {
        "text": "澥",
        "meaning": "묽을,바다",
        "strokeCount": "16"
      },
      {
        "text": "瀣",
        "meaning": "이슬기운",
        "strokeCount": "19"
      },
      {
        "text": "獬",
        "meaning": "해태",
        "strokeCount": "16"
      },
      {
        "text": "瑎",
        "meaning": "검은옥돌",
        "strokeCount": "13"
      },
      {
        "text": "痎",
        "meaning": "학질",
        "strokeCount": "11"
      },
      {
        "text": "祄",
        "meaning": "하늘이 도울",
        "strokeCount": "8"
      },
      {
        "text": "絯",
        "meaning": "묽을,걸,굵은실",
        "strokeCount": "12"
      },
      {
        "text": "荄",
        "meaning": "풀뿌리",
        "strokeCount": "9"
      },
      {
        "text": "薤",
        "meaning": "염교",
        "strokeCount": "19"
      },
      {
        "text": "蟹",
        "meaning": "게",
        "strokeCount": "19"
      },
      {
        "text": "解",
        "meaning": "풀",
        "strokeCount": "13"
      },
      {
        "text": "該",
        "meaning": "갖출,맞을,그",
        "strokeCount": "13"
      },
      {
        "text": "諧",
        "meaning": "어울릴,고를,농짓거리",
        "strokeCount": "16"
      },
      {
        "text": "賅",
        "meaning": "갖출",
        "strokeCount": "13"
      },
      {
        "text": "邂",
        "meaning": "만날",
        "strokeCount": "17"
      },
      {
        "text": "郋",
        "meaning": "마을이름",
        "strokeCount": "8"
      },
      {
        "text": "醢",
        "meaning": "육장",
        "strokeCount": "17"
      },
      {
        "text": "陔",
        "meaning": "층계",
        "strokeCount": "9"
      },
      {
        "text": "頦",
        "meaning": "턱밑",
        "strokeCount": "15"
      },
      {
        "text": "駭",
        "meaning": "놀날",
        "strokeCount": "16"
      },
      {
        "text": "骸",
        "meaning": "해골",
        "strokeCount": "16"
      },
      {
        "text": "鮭",
        "meaning": "어채,북어",
        "strokeCount": "17"
      },
      {
        "text": "龤",
        "meaning": "노래의가락이조화될",
        "strokeCount": "26"
      }
    ]
  }
]