[
  {
    "text": "호",
    "hanja": [
      {
        "text": "乎",
        "meaning": "어조사",
        "strokeCount": "5"
      },
      {
        "text": "互",
        "meaning": "서로",
        "strokeCount": "4"
      },
      {
        "text": "儫",
        "meaning": "영웅",
        "strokeCount": "16"
      },
      {
        "text": "冱",
        "meaning": "얼,추위",
        "strokeCount": "6"
      },
      {
        "text": "号",
        "meaning": "부르짖을",
        "strokeCount": "5"
      },
      {
        "text": "呼",
        "meaning": "숨내쉴",
        "strokeCount": "8"
      },
      {
        "text": "哠",
        "meaning": "말많을",
        "strokeCount": "10"
      },
      {
        "text": "唬",
        "meaning": "으를",
        "strokeCount": "11"
      },
      {
        "text": "嘷",
        "meaning": "짖을",
        "strokeCount": "15"
      },
      {
        "text": "嚎",
        "meaning": "울부짖을",
        "strokeCount": "17"
      },
      {
        "text": "垀",
        "meaning": "낮은담,번거러울",
        "strokeCount": "8"
      },
      {
        "text": "壕",
        "meaning": "해자",
        "strokeCount": "17"
      },
      {
        "text": "壺",
        "meaning": "병",
        "strokeCount": "12"
      },
      {
        "text": "好",
        "meaning": "좋을,좋아할",
        "strokeCount": "6"
      },
      {
        "text": "婋",
        "meaning": "계집영리할",
        "strokeCount": "11"
      },
      {
        "text": "嫭",
        "meaning": "아름다울,자랑할",
        "strokeCount": "14"
      },
      {
        "text": "嫮",
        "meaning": "아름다울,자랑할",
        "strokeCount": "14"
      },
      {
        "text": "岵",
        "meaning": "산",
        "strokeCount": "8"
      },
      {
        "text": "弧",
        "meaning": "활",
        "strokeCount": "8"
      },
      {
        "text": "怙",
        "meaning": "믿을,아비",
        "strokeCount": "8"
      },
      {
        "text": "戶",
        "meaning": "지게",
        "strokeCount": "4"
      },
      {
        "text": "扈",
        "meaning": "따를",
        "strokeCount": "11"
      },
      {
        "text": "昈",
        "meaning": "문채날,밝을",
        "strokeCount": "8"
      },
      {
        "text": "昊",
        "meaning": "하늘",
        "strokeCount": "8"
      },
      {
        "text": "晧",
        "meaning": "밝을,빛",
        "strokeCount": "11"
      },
      {
        "text": "暤",
        "meaning": "밝을",
        "strokeCount": "14"
      },
      {
        "text": "枑",
        "meaning": "울짱",
        "strokeCount": "8"
      },
      {
        "text": "楛",
        "meaning": "나무이름",
        "strokeCount": "12"
      },
      {
        "text": "楜",
        "meaning": "후추",
        "strokeCount": "13"
      },
      {
        "text": "毫",
        "meaning": "잔털,붓,조금",
        "strokeCount": "11"
      },
      {
        "text": "沍",
        "meaning": "얼,추위",
        "strokeCount": "7"
      },
      {
        "text": "浩",
        "meaning": "넓을",
        "strokeCount": "10"
      },
      {
        "text": "淏",
        "meaning": "맑을",
        "strokeCount": "11"
      },
      {
        "text": "湖",
        "meaning": "호수",
        "strokeCount": "12"
      },
      {
        "text": "滈",
        "meaning": "장마",
        "strokeCount": "13"
      },
      {
        "text": "滬",
        "meaning": "물이름,대어살",
        "strokeCount": "14"
      },
      {
        "text": "滸",
        "meaning": "물가",
        "strokeCount": "14"
      },
      {
        "text": "滹",
        "meaning": "물이름",
        "strokeCount": "14"
      },
      {
        "text": "澔",
        "meaning": "물펀질할,넓고클",
        "strokeCount": "15"
      },
      {
        "text": "濠",
        "meaning": "해자",
        "strokeCount": "17"
      },
      {
        "text": "濩",
        "meaning": "퍼질,풍류",
        "strokeCount": "17"
      },
      {
        "text": "灝",
        "meaning": "아득할",
        "strokeCount": "24"
      },
      {
        "text": "熩",
        "meaning": "빛",
        "strokeCount": "15"
      },
      {
        "text": "犒",
        "meaning": "호궤할",
        "strokeCount": "14"
      },
      {
        "text": "狐",
        "meaning": "여우",
        "strokeCount": "8"
      },
      {
        "text": "猢",
        "meaning": "원숭이",
        "strokeCount": "12"
      },
      {
        "text": "琥",
        "meaning": "호박",
        "strokeCount": "12"
      },
      {
        "text": "瑚",
        "meaning": "산호",
        "strokeCount": "13"
      },
      {
        "text": "瓠",
        "meaning": "표주박",
        "strokeCount": "11"
      },
      {
        "text": "瓳",
        "meaning": "벽돌",
        "strokeCount": "9"
      },
      {
        "text": "皓",
        "meaning": "밝을",
        "strokeCount": "12"
      },
      {
        "text": "皜",
        "meaning": "밝을",
        "strokeCount": "15"
      },
      {
        "text": "皞",
        "meaning": "짖을",
        "strokeCount": "15"
      },
      {
        "text": "祜",
        "meaning": "복",
        "strokeCount": "10"
      },
      {
        "text": "糊",
        "meaning": "풀,바를",
        "strokeCount": "15"
      },
      {
        "text": "縞",
        "meaning": "명주,흴",
        "strokeCount": "16"
      },
      {
        "text": "聕",
        "meaning": "들릴,긴귀",
        "strokeCount": "13"
      },
      {
        "text": "胡",
        "meaning": "오랑캐,어찌",
        "strokeCount": "9"
      },
      {
        "text": "芐",
        "meaning": "지황",
        "strokeCount": "6"
      },
      {
        "text": "芦",
        "meaning": "지황,부들",
        "strokeCount": "10"
      },
      {
        "text": "葫",
        "meaning": "마늘",
        "strokeCount": "15"
      },
      {
        "text": "蒿",
        "meaning": "쑥",
        "strokeCount": "16"
      },
      {
        "text": "蔰",
        "meaning": "빛",
        "strokeCount": "14"
      },
      {
        "text": "虍",
        "meaning": "범의무늬",
        "strokeCount": "6"
      },
      {
        "text": "虎",
        "meaning": "호랑이",
        "strokeCount": "6"
      },
      {
        "text": "號",
        "meaning": "이름,차례,부를",
        "strokeCount": "11"
      },
      {
        "text": "蝴",
        "meaning": "나비",
        "strokeCount": "15"
      },
      {
        "text": "護",
        "meaning": "지킬,도울",
        "strokeCount": "21"
      },
      {
        "text": "譹",
        "meaning": "부르짖을",
        "strokeCount": "21"
      },
      {
        "text": "豪",
        "meaning": "호저,뛰어날",
        "strokeCount": "14"
      },
      {
        "text": "醐",
        "meaning": "우락더껑이",
        "strokeCount": "16"
      },
      {
        "text": "鍸",
        "meaning": "쇠접시",
        "strokeCount": "17"
      },
      {
        "text": "鎬",
        "meaning": "남비,호경,빛날",
        "strokeCount": "18"
      },
      {
        "text": "頀",
        "meaning": "풍류",
        "strokeCount": "23"
      },
      {
        "text": "顥",
        "meaning": "클,빛날",
        "strokeCount": "21"
      },
      {
        "text": "餬",
        "meaning": "기식할",
        "strokeCount": "18"
      },
      {
        "text": "鬍",
        "meaning": "수염",
        "strokeCount": "19"
      }
    ]
  }
]